Workbook

Sheet Datos
A1: Producto | B1: Cantidad | C1: precio compra x u | D1: Precio base | E1: precio comprado | F1: total cantidad preciobase | H1: producto vendidos | I1: precio vendido
A2: Lapiz ojos (azul) | B2: 2 | C2: 3 | D2: 6 | F2: =B2*D2 -> 12 | H2: Ice combo | I2: 10 | K2: =I2-C15 -> 7
A3: Lapiz de ojos (negro) | B3: 3 | C3: 2.5 | D3: 5.5 | F3: =B3*D3 -> 16.5 | H3: lapiz ojos negros | I3: 5.5 | K3: =I3-C3 -> 3
A4: Pestañina | B4: 5 | C4: 4 | D4: 6.5 | F4: =B4*D4 -> 32.5 | H4: combo completo | I4: 24.9 | K4: =I4-C16 -> 11.9
A5: Lapiz de labios (rojo) | B5: 2 | C5: 3 | D5: 6 | F5: =B5*D5 -> 12 | H5: labiales | I5: 15 | K5: =I5-C7 -> 11
A6: Lapiz de labios (café) | B6: 3 | C6: 2.5 | D6: 5 | F6: =B6*D6 -> 15 | H6: lapiz ojos negros | I6: 5.5 | K6: =I6-C3 -> 3
A7: Labial (rojo) | B7: 2 | C7: 4 | D7: 7 | F7: =B7*D7 -> 14 | H7: labial | I7: 5.3 | K7: =I7-C5 -> 2.3
A8: Labial (Rosado) | B8: 2 | C8: 4 | D8: 7 | F8: =B8*D8 -> 14 | H8: gloss | I8: 6 | K8: =I8-C11 -> 3
A9: Labial (Morado) | B9: 1 | C9: 4.5 | D9: 8 | F9: =B9*D9 -> 8 | H9: combo pequeño | I9: 10 | K9: =I9-C15 -> 7
A10: Gloss (morado) | B10: 2 | C10: 3.5 | D10: 6 | F10: =B10*D10 -> 12 | H10: gloss | I10: 3 | K10: =I10-C11 -> 0
A11: Gloss (rojo) | B11: 1 | C11: 3 | D11: 6 | F11: =B11*D11 -> 6 | H11: labial | I11: 3 | K11: =I11-C6 -> 0.5
A12: Gloss (azul) | B12: 2 | C12: 3.5 | D12: 6 | F12: =B12*D12 -> 12
A13: Paquetes | B13: 15 | F13: =B13*D13 -> 0
A14: Lip combo | B14: 5 | C14: 8.5 | D14: 18.9 | F14: =B14*D14 -> 94.5
A15: Eyes combo | B15: 5 | C15: 3 | D15: 10 | F15: =B15*D15 -> 50
A16: Combo completo | B16: 5 | C16: 13 | D16: 26.9 | F16: =B16*D16 -> 134.5
D19: =SUM(D16,D15,D14,D13,D12,D11,D10,D9,D8,D2,D3,D4,D5,D6,D7) -> 124.8 | E19: =SUM(E16,E15,E14,E13,E12,E11,E10,E9,E8,E2,E3,E4,E5,E6,E7) -> 0 | F19: =SUM(F16,F15,F14,F13,F12,F11,F10,F9,F8,F2,F3,F4,F5,F6,F7) -> 433 | G19: =SUM(G16,G15,G14,G13,G12,G11,G10,G9,G8,G2,G3,G4,G5,G6,G7) -> 0 | H19: =SUM(H16,H15,H14,H13,H12,H11,H10,H9,H8,H2,H3,H4,H5,H6,H7) -> 0 | I19: =SUM(I16,I15,I14,I13,I12,I11,I10,I9,I8,I2,I3,I4,I5,I6,I7) -> 88.2 | J19: =SUM(J16,J15,J14,J13,J12,J11,J10,J9,J8,J2,J3,J4,J5,J6,J7) -> 0 | K19: =SUM(K16,K15,K14,K13,K12,K11,K10,K9,K8,K2,K3,K4,K5,K6,K7) -> 48.7
F21: 433000

Sheet Limpieza
A1: clientes | B1: id_producto vendido | C1: producto | D1: precio vendido | E1: precio real | F1: diferencia
A2: 1 | B2: 1234 | C2: Eyes combo (paquete 2) | D2: 10 | E2: 10 | F2: =E2-D2 -> 0
A3: 2 | B3: 1235 | C3: Lapiz de ojos (negro) | D3: 5.5 | E3: 5.5 | F3: =E3-D3 -> 0
A4: 3 | B4: 1236 | C4: Lapiz de ojos (negro) | D4: 5.5 | E4: 5.5 | F4: =E4-D4 -> 0
A5: 4 | B5: 1237 | C5: Combo completo (paquete 3) | D5: 24.9 | E5: 26.9 | F5: =E5-D5 -> 2
A6: 5 | B6: 1238 | C6: Labial (rojo) | D6: 5 | E6: 7 | F6: =E6-D6 -> 2
A7: 6 | B7: 1239 | C7: Labial (rosado) | D7: 5 | E7: 7 | F7: =E7-D7 -> 2
A8: 7 | B8: 1230 | C8: Labial (morado) | D8: 5 | E8: 8 | F8: =E8-D8 -> 3
A9: 8 | B9: 2234 | C9: Labial (morado) | D9: 5.3 | E9: 8 | F9: =E9-D9 -> 2.7
A10: 9 | B10: 2235 | C10: Gloss (azul) | D10: 6 | E10: 6 | F10: =E10-D10 -> 0
A11: 10 | B11: 2236 | C11: Eyes combo (paquete 2) | D11: 10 | E11: 10 | F11: =E11-D11 -> 0
A12: 11 | B12: 2237 | C12: Gloss (rojo) | D12: 3 | E12: 6 | F12: =E12-D12 -> 3
A13: 12 | B13: 2238 | C13: Labial (Rosado) | D13: 3 | E13: 7 | F13: =E13-D13 -> 4
... A15: 14 | B15: 2230 | C15: Lip combo (paquete 1) | D15: 15.8 | E15: 18.9 | F15: =E15-D15 -> 3.1
A16: 15 | B16: 3234 | C16: Eyes combo (paquete 2) | D16: 10 | E16: 10 | F16: =E16-D16 -> 0 | I16: =COUNTIF(Limpieza!$C$3:$C$21, A3) -> 0
A17: 16 | B17: 3235 | C17: Eyes combo (paquete 2) | D17: 8.9 | E17: 10 | F17: =E17-D17 -> 1.1
A18: 17 | B18: 3236 | C18: Combo completo (paquete 3) | D18: 25.9 | E18: 26.9 | F18: =E18-D18 -> 1
A19: 18 | B19: 3237 | C19: Combo completo (paquete 3) | D19: 26.9 | E19: 26.9 | F19: =E19-D19 -> 0
A20: 19 | B20: 3238 | C20: Lapiz de ojos (azul) promoción | D20: 2.5 | E20: 6 | F20: =E20-D20 -> 3.5
A21: 20 | B21: 3239 | C21: Lapiz de ojos (azul) promoción | D21: 2.5 | E21: 6 | F21: =E21-D21 -> 3.5
A24: Nulos | B24: =COUNTBLANK(B1:B21) -> 0 | C24: =COUNTBLANK(C1:C21) -> 0 | D24: =COUNTBLANK(D1:D21) -> 0 | E24: =COUNTBLANK(E1:E21) -> 0 | F24: =COUNTBLANK(F1:F21) -> 0
A25: Duplicados | B25: =IF(COUNTIF($B$2:$B$21,B2)>1,"Duplicado","Único") -> Único | C25: =COUNTIF($C$2:$C$21, C2) -> 4

Sheet Univariado
B4: A. Descriptivas del Precio Vendido (precio vendido en columna D) | E4: B. Cuartiles y Detección de Outliers (Valores Atípicos en Ventas) | H4: C. Frecuencia y Distribución por Producto
B5: Total de ventas realizadas | C5: =COUNT(Limpieza!$D$2:$D$21) -> 20 | E5: Primer cuartil | F5: =_xlfn.QUARTILE.INC(Limpieza!$D$2:$D$21, 1) -> 5 | I5: =COUNTIF(Limpieza!$C$2:$C$21, A2) -> 0
B6: Total de ingresos generados | C6: =SUM(Limpieza!$D$2:$D$21) -> 196.7 | E6: Mediana | F6: =MEDIAN(Limpieza!$D$2:$D$21) -> 5.75 | I6: =COUNTIF(Limpieza!$C$2:$C$21, A3) -> 0
B7: Precio vendio promedio | C7: =AVERAGE(Limpieza!$D$2:$D$21) -> 9.835 | E7: Tercer cuartil | F7: =_xlfn.QUARTILE.INC(Limpieza!$D$2:$D$21, 3) -> 11.45 | I7: =COUNTIF(Limpieza!$C$2:$C$21, A4) -> 0
B8: Precio vendido minimo | C8: =MIN(Limpieza!$D$2:$D$21) -> 2.5 | E8: Limite inferior | F8: =F5 - 1.5 * (F5-F7) -> 14.675 | I8: =COUNTIF(Limpieza!$C$2:$C$21, A5) -> 0
B9: precio vendido maximo | C9: =MAX(Limpieza!$D$2:$D$21) -> 26.9 | E9: Limite superior | F9: =F7 + 1.5 *(F7-F5) -> 21.125 | I9: =COUNTIF(Limpieza!$C$2:$C$21, A6) -> 0
B10: Desviación estándar de ventas | C10: =_xlfn.STDEV.S(Limpieza!$D$2:$D$21) -> 7.9300411 | I10: =COUNTIF(Limpieza!$C$2:$C$21, A7) -> 0
I11: =COUNTIF(Limpieza!$C$2:$C$21, A8) -> 0
I12: =COUNTIF(Limpieza!$C$2:$C$21, A9) -> 0
I13: =COUNTIF(Limpieza!$C$2:$C$21, A10) -> 0
I14: =COUNTIF(Limpieza!$C$2:$C$21, A11) -> 0
I15: =COUNTIF(Limpieza!$C$2:$C$21, A12) -> 0
I16: =COUNTIF(Limpieza!$C$2:$C$21, A13) -> 0
I17: =COUNTIF(Limpieza!$C$2:$C$21, A14) -> 0
I18: =COUNTIF(Limpieza!$C$2:$C$21, A15) -> 0
I19: =COUNTIF(Limpieza!$C$2:$C$21, A16) -> 0
I20: =COUNTIF(Limpieza!$C$2:$C$21, A17) -> 0
I21: =COUNTIF(Limpieza!$C$2:$C$21, A18) -> 0
I22: =COUNTIF(Limpieza!$C$2:$C$21, A19) -> 0
... I24: =COUNTIF(Limpieza!$C$2:$C$21, A21) -> 0

Sheet Bivariado
A3: {=A3:E14producto} -> #NAME? | B3: unidades vendidas | C3: Ingreso total | D3: precio promedio | E3: descuento total
A4: Combo completo (paquete 3) | B4: =COUNTIF(Limpieza!$C$2:$C$21, A4) -> 0 | C4: =SUMIF(Limpieza!$C$2:$C$21, A4, Limpieza!$D$2:$D$21) -> 0 | D4: =IFERROR(AVERAGEIF(Limpieza!$C$2:$C$21, A4, Limpieza!$D$2:$D$21), 0) -> 0 | E4: =SUMIF(Limpieza!$C$2:$C$21, A4, Limpieza!$F$2:$F$21) -> 0
A5: Eyes combo (paquete 2) | B5: =COUNTIF(Limpieza!$C$2:$C$21, A5) -> 0 | C5: =SUMIF(Limpieza!$C$2:$C$21, A5, Limpieza!$D$2:$D$21) -> 0 | D5: =IFERROR(AVERAGEIF(Limpieza!$C$2:$C$21, A5, Limpieza!$D$2:$D$21), 0) -> 0 | E5: =SUMIF(Limpieza!$C$2:$C$21, A5, Limpieza!$F$2:$F$21) -> 0
A6: Lapiz de ojos (negro) | B6: =COUNTIF(Limpieza!$C$2:$C$21, A6) -> 2 | C6: =SUMIF(Limpieza!$C$2:$C$21, A6, Limpieza!$D$2:$D$21) -> 11 | D6: =IFERROR(AVERAGEIF(Limpieza!$C$2:$C$21, A6, Limpieza!$D$2:$D$21), 0) -> 5.5 | E6: =SUMIF(Limpieza!$C$2:$C$21, A6, Limpieza!$F$2:$F$21) -> 0
A7: Lapiz de ojos (negro) | B7: =COUNTIF(Limpieza!$C$2:$C$21, A7) -> 2 | C7: =SUMIF(Limpieza!$C$2:$C$21, A7, Limpieza!$D$2:$D$21) -> 11 | D7: =IFERROR(AVERAGEIF(Limpieza!$C$2:$C$21, A7, Limpieza!$D$2:$D$21), 0) -> 5.5 | E7: =SUMIF(Limpieza!$C$2:$C$21, A7, Limpieza!$F$2:$F$21) -> 0
A8: Labial (morado) | B8: =COUNTIF(Limpieza!$C$2:$C$21, A8) -> 2 | C8: =SUMIF(Limpieza!$C$2:$C$21, A8, Limpieza!$D$2:$D$21) -> 10.3 | D8: =IFERROR(AVERAGEIF(Limpieza!$C$2:$C$21, A8, Limpieza!$D$2:$D$21), 0) -> 5.15 | E8: =SUMIF(Limpieza!$C$2:$C$21, A8, Limpieza!$F$2:$F$21) -> 5.7
A9: Gloss (azul) | B9: =COUNTIF(Limpieza!$C$2:$C$21, A9) -> 1 | C9: =SUMIF(Limpieza!$C$2:$C$21, A9, Limpieza!$D$2:$D$21) -> 6 | D9: =IFERROR(AVERAGEIF(Limpieza!$C$2:$C$21, A9, Limpieza!$D$2:$D$21), 0) -> 6 | E9: =SUMIF(Limpieza!$C$2:$C$21, A9, Limpieza!$F$2:$F$21) -> 0
A10: Labial (rojo) | B10: =COUNTIF(Limpieza!$C$2:$C$21, A10) -> 0 | C10: =SUMIF(Limpieza!$C$2:$C$21, A10, Limpieza!$D$2:$D$21) -> 0 | D10: =IFERROR(AVERAGEIF(Limpieza!$C$2:$C$21, A10, Limpieza!$D$2:$D$21), 0) -> 0 | E10: =SUMIF(Limpieza!$C$2:$C$21, A10, Limpieza!$F$2:$F$21) -> 0
A11: Labial (rosado) | B11: =COUNTIF(Limpieza!$C$2:$C$21, A11) -> 0 | C11: =SUMIF(Limpieza!$C$2:$C$21, A11, Limpieza!$D$2:$D$21) -> 0 | D11: =IFERROR(AVERAGEIF(Limpieza!$C$2:$C$21, A11, Limpieza!$D$2:$D$21), 0) -> 0 | E11: =SUMIF(Limpieza!$C$2:$C$21, A11, Limpieza!$F$2:$F$21) -> 0
A12: Lapiz de ojos (azul) promoción | B12: =COUNTIF(Limpieza!$C$2:$C$21, A12) -> 2 | C12: =SUMIF(Limpieza!$C$2:$C$21, A12, Limpieza!$D$2:$D$21) -> 5 | D12: =IFERROR(AVERAGEIF(Limpieza!$C$2:$C$21, A12, Limpieza!$D$2:$D$21), 0) -> 2.5 | E12: =SUMIF(Limpieza!$C$2:$C$21, A12, Limpieza!$F$2:$F$21) -> 7
A13: Gloss (rojo) | B13: =COUNTIF(Limpieza!$C$2:$C$21, A13) -> 0 | C13: =SUMIF(Limpieza!$C$2:$C$21, A13, Limpieza!$D$2:$D$21) -> 0 | D13: =IFERROR(AVERAGEIF(Limpieza!$C$2:$C$21, A13, Limpieza!$D$2:$D$21), 0) -> 0 | E13: =SUMIF(Limpieza!$C$2:$C$21, A13, Limpieza!$F$2:$F$21) -> 0
A14: Labial (Rosado) | B14: =COUNTIF(Limpieza!$C$2:$C$21, A14) -> 0 | C14: =SUMIF(Limpieza!$C$2:$C$21, A14, Limpieza!$D$2:$D$21) -> 0 | D14: =IFERROR(AVERAGEIF(Limpieza!$C$2:$C$21, A14, Limpieza!$D$2:$D$21), 0) -> 0 | E14: =SUMIF(Limpieza!$C$2:$C$21, A14, Limpieza!$F$2:$F$21) -> 0
I16: =SUMIF(Limpieza!$C$2:$C$21,#REF!, Limpieza!$F$2:$F$21) -> 0
C17: =SUMIF(Limpieza!$C$2:$C$21, A15, Limpieza!$D$2:$D$21) -> 0
C18: =SUMIF(Limpieza!$C$2:$C$21, A16, Limpieza!$D$2:$D$21) -> 0
C19: =SUMIF(Limpieza!$C$2:$C$21, A17, Limpieza!$D$2:$D$21) -> 0 | F19: =AVERAGEIF(Limpieza!$C$2:$C$21, A17, Limpieza!$D$2:$D$21) -> #DIV/0!
C20: =SUMIF(Limpieza!$C$2:$C$21, A18, Limpieza!$D$2:$D$21) -> 0 | F20: =AVERAGEIF(Limpieza!$C$2:$C$21, A18, Limpieza!$D$2:$D$21) -> #DIV/0!
C21: =SUMIF(Limpieza!$C$2:$C$21, A19, Limpieza!$D$2:$D$21) -> 0 | F21: =AVERAGEIF(Limpieza!$C$2:$C$21, A19, Limpieza!$D$2:$D$21) -> #DIV/0!
C22: =SUMIF(Limpieza!$C$2:$C$21, A20, Limpieza!$D$2:$D$21) -> 0 | F22: =AVERAGEIF(Limpieza!$C$2:$C$21, A20, Limpieza!$D$2:$D$21) -> #DIV/0!
C23: =SUMIF(Limpieza!$C$2:$C$21, A21, Limpieza!$D$2:$D$21) -> 0 | F23: =AVERAGEIF(Limpieza!$C$2:$C$21, A21, Limpieza!$D$2:$D$21) -> #DIV/0!
